practica3/contador_8bits.v
module contador_8bits (
        input wire clk,        // Reloj
        input wire rst,        // Reset
        output reg [7:0] count // Salida del contador de 8 bits
    );

    always @(posedge clk or posedge rst) begin
        if (rst) begin
            count <= 8'b0;  // Si rst está activo, el contador se reinicia a 0
        end else begin
            count <= count + 1'b1;  // Incrementa el contador en cada ciclo de reloj
        end
    end
endmodule

practica3/contador_8bits.vt
`timescale 1ns / 1ps

module tb_contador_8bits;

    // Declaración de señales
    reg clk;                // Señal de reloj
    reg rst;                // Señal de reset
    wire [7:0] count;      // Salida del contador

    // Instancia del módulo contador
    contador_8bits uut (
        .clk(clk),
        .rst(rst),
        .count(count)
    );

    // Generación de la señal de reloj
    initial begin
        clk = 0;
        forever #5 clk = ~clk; // Cambia el reloj cada 5 ns
    end

    // Proceso de prueba
    initial begin
        // Inicialización
        rst = 1;              // Activa el reset
        #10;                  // Espera 10 ns
        rst = 0;              // Desactiva el reset

        // Simulación de conteo
        #100;                 // Espera 100 ns
        rst = 1;              // Activa el reset
        #10;                  // Espera 10 ns
        rst = 0;              // Desactiva el reset

        // Continuar la simulación
        #200;                 // Espera otros 200 ns
        rst = 1;              // Activa el reset de nuevo
        #10;                  // Espera 10 ns
        rst = 0;              // Desactiva el reset

        // Finaliza la simulación
        #50;                  // Espera 50 ns
        $stop;               // Detiene la simulación
    end

    // Monitor para observar el valor del contador
    initial begin
        $monitor("Time: %0t | Reset: %b | Count: %h", $time, rst, count);
    end

endmodule

practica3/tb_contador_8bits_result.vcd
$date
	Thu Sep 19 18:38:25 2024
$end
$version
	Icarus Verilog
$end
$timescale
	1ps
$end
$scope module tb_contador_8bits $end
$var wire 8 ! count [7:0] $end
$var reg 1 " clk $end
$var reg 1 # rst $end
$scope module uut $end
$var wire 1 " clk $end
$var wire 1 # rst $end
$var reg 8 $ count [7:0] $end
$upscope $end
$upscope $end
$enddefinitions $end
#0
$dumpvars
b0 $
1#
0"
b0 !
$end
#5000
1"
#10000
0"
0#
#15000
b1 !
b1 $
1"
#20000
0"
#25000
b10 !
b10 $
1"
#30000
0"
#35000
b11 !
b11 $
1"
#40000
0"
#45000
b100 !
b100 $
1"
#50000
0"
#55000
b101 !
b101 $
1"
#60000
0"
#65000
b110 !
b110 $
1"
#70000
0"
#75000
b111 !
b111 $
1"
#80000
0"
#85000
b1000 !
b1000 $
1"
#90000
0"
#95000
b1001 !
b1001 $
1"
#100000
0"
#105000
b1010 !
b1010 $
1"
#110000
b0 !
b0 $
0"
1#
#115000
1"
#120000
0"
0#
#125000
b1 !
b1 $
1"
#130000
0"
#135000
b10 !
b10 $
1"
#140000
0"
#145000
b11 !
b11 $
1"
#150000
0"
#155000
b100 !
b100 $
1"
#160000
0"
#165000
b101 !
b101 $
1"
#170000
0"
#175000
b110 !
b110 $
1"
#180000
0"
#185000
b111 !
b111 $
1"
#190000
0"
#195000
b1000 !
b1000 $
1"
#200000
0"
#205000
b1001 !
b1001 $
1"
#210000
0"
#215000
b1010 !
b1010 $
1"
#220000
0"
#225000
b1011 !
b1011 $
1"
#230000
0"
#235000
b1100 !
b1100 $
1"
#240000
0"
#245000
b1101 !
b1101 $
1"
#250000
0"
#255000
b1110 !
b1110 $
1"
#260000
0"
#265000
b1111 !
b1111 $
1"
#270000
0"
#275000
b10000 !
b10000 $
1"
#280000
0"
#285000
b10001 !
b10001 $
1"
#290000
0"
#295000
b10010 !
b10010 $
1"
#300000
0"
#305000
b10011 !
b10011 $
1"
#310000
0"
#315000
b10100 !
b10100 $
1"
#320000
b0 !
b0 $
0"
1#
#325000
1"
#330000
0"
0#
#335000
b1 !
b1 $
1"
#340000
0"
#345000
b10 !
b10 $
1"
#350000
0"
#355000
b11 !
b11 $
1"
#360000
0"
#365000
b100 !
b100 $
1"
#370000
0"
#375000
b101 !
b101 $
1"
